mqtt_middlware_utils/__init__.py
mqtt_middlware_utils/db_utils.py
mqtt_middlware_utils/logging_utils.py
mqtt_middlware_utils/utils.py
mqtt_middlware_utils/exceptions/__init__.py
mqtt_middlware_utils/exceptions/mqtt_middleware_exceptions.py
mqtt_middleware_utils-1.0.6.dist-info/LICENSE.txt
mqtt_middleware_utils-1.0.6.dist-info/METADATA
mqtt_middleware_utils-1.0.6.dist-info/WHEEL
mqtt_middleware_utils-1.0.6.dist-info/top_level.txt
mqtt_middleware_utils-1.0.6.dist-info/RECORD
