Metadata-Version: 2.1
Name: mqtt_middleware_utils
Version: 1.0.6
Summary: MQTT Middleware package containing all functions that must be shared between FaaS projects
Author-email: Andrea Ranfone <andrea.ranfone@top-network.it>
Classifier: Programming Language :: Python :: 3
Classifier: License :: OSI Approved :: MIT License
Classifier: Operating System :: OS Independent
Requires-Python: >=3.8.10
License-File: LICENSE.txt
Requires-Dist: redis >=5.0.1
Requires-Dist: fabric >=3.2.2
Requires-Dist: pytest >=7.4.2
